{
    "player": "Pemain",
    "player_pair": "Pair Pemain",
    "player_bonus": "Bonus Pemain",
    "tie": "Seri",
    "perfect_pair": "Pair Sempurna",
    "mixed_pair": "Pair Campuran",
    "banker": "Bankir",
    "banker_bonus": "Bonus Bankir",
    "banker_pair": "Pair Bankir",
    "small": "Kecil",
    "big": "Besar",
    "player pair": "Pair Pemain",
    "player bonus": "Bonus Pemain",
    "perfect pair": "Pair Sempurna",
    "mixed pair": "Pair Campuran",
    "banker bonus": "Bonus Bankir",
    "banker pair": "Pair Bankir",
    "side bet": "Taruhan Sampingan",
    "tie on": "Seri",
    "0": "0",
    "1": "1",
    "2": "2",
    "3": "3",
    "4": "4",
    "5": "5",
    "6": "6",
    "7": "7",
    "8": "8",
    "9": "9",
    "natural win": "Menang Natural",
    "natural tie": "Tie Natural",
    "win by 9 points": "Menang 9 poin",
    "win by 8 points": "Menang 8 poin",
    "win by 7 points": "Menang 7 poin",
    "win by 6 points": "Menang 6 poin",
    "win by 5 points": "Menang 5 poin",
    "win by 4 points": "Menang 4 poin"
}
